wallhavenapi/__init__.py
wallhavenapi/wallhavenapi.py
wallhavenapi-0.1.0.dist-info/LICENSE
wallhavenapi-0.1.0.dist-info/METADATA
wallhavenapi-0.1.0.dist-info/WHEEL
wallhavenapi-0.1.0.dist-info/top_level.txt
wallhavenapi-0.1.0.dist-info/RECORD
