Metadata-Version: 2.1
Name: wallhavenapi
Version: 0.1.0
Summary: A Python wrapper for the Wallhaven.cc API v1.
Author-email: Ray Cadle <you@example.com>
License: MIT
Project-URL: Homepage, https://github.com/raycadle/WallhavenAPI
Project-URL: Repository, https://github.com/raycadle/WallhavenAPI
Project-URL: Issues, https://github.com/raycadle/WallhavenAPI/issues
Keywords: wallhaven,api,wallpaper,image,wrapper
Classifier: Programming Language :: Python :: 3
Classifier: License :: OSI Approved :: MIT License
Classifier: Operating System :: OS Independent
Classifier: Intended Audience :: Developers
Classifier: Topic :: Internet :: WWW/HTTP :: Indexing/Search
Classifier: Topic :: Multimedia :: Graphics
Requires-Python: >=3.8
License-File: LICENSE
Requires-Dist: requests>=2.0
